stollen/__init__.py
stollen/__meta__.py
stollen/const.py
stollen/exceptions.py
stollen/loggers.py
stollen/method.py
stollen/object.py
stollen/py.typed
stollen/types.py
stollen/client/__init__.py
stollen/client/client.py
stollen/client/context_controller.py
stollen/enums/__init__.py
stollen/enums/http_method.py
stollen/enums/request_field_type.py
stollen/requests/__init__.py
stollen/requests/factory.py
stollen/requests/fields.py
stollen/requests/input_file.py
stollen/requests/serializer.py
stollen/requests/types.py
stollen/session/__init__.py
stollen/session/base.py
stollen/session/aiohttp/__init__.py
stollen/session/aiohttp/proxy.py
stollen/session/aiohttp/session.py
stollen/utils/__init__.py
stollen/utils/mapping.py
stollen/utils/text.py
stollen-0.8.1.dist-info/METADATA
stollen-0.8.1.dist-info/WHEEL
stollen-0.8.1.dist-info/licenses/LICENSE
stollen-0.8.1.dist-info/RECORD
