Metadata-Version: 2.4
Name: stollen
Version: 0.8.1
Summary: An asynchronous framework to easily build a client-side API
Project-URL: Source, https://github.com/py-stollen/stollen
Project-URL: Issues, https://github.com/py-stollen/stollen/issues
Author-email: wakaree <nullmatawasoradesu@gmail.com>
Maintainer-email: wakaree <nullmatawasoradesu@gmail.com>
License-Expression: MIT
License-File: LICENSE
Keywords: api,asyncio,client,framework,wrapper
Classifier: Development Status :: 4 - Beta
Classifier: Environment :: Console
Classifier: Framework :: AsyncIO
Classifier: License :: OSI Approved :: MIT License
Classifier: Programming Language :: Python :: 3.9
Classifier: Programming Language :: Python :: 3.10
Classifier: Programming Language :: Python :: 3.11
Classifier: Programming Language :: Python :: 3.12
Classifier: Topic :: Software Development :: Libraries :: Python Modules
Classifier: Typing :: Typed
Requires-Python: >=3.9
Requires-Dist: aiofiles<26.0,>=23.2.1
Requires-Dist: aiohttp<3.15,>=3.9.0
Requires-Dist: certifi>=2023.7.22
Requires-Dist: pydantic<2.15,>=2.4.1
Requires-Dist: typing-extensions<=5.0,>=4.7.0
Provides-Extra: dev
Requires-Dist: mypy~=1.10.0; extra == 'dev'
Requires-Dist: pre-commit~=3.6; extra == 'dev'
Requires-Dist: ruff~=0.6.0; extra == 'dev'
Requires-Dist: types-aiofiles>=24.1.0.20240626; extra == 'dev'
Requires-Dist: types-xmltodict>=1.0.1.20250920; extra == 'dev'
Provides-Extra: proxy
Requires-Dist: aiohttp-socks<0.10,>=0.8; extra == 'proxy'
